clck/__init__.py
clck_ru_api-1.0.0.dist-info/METADATA
clck_ru_api-1.0.0.dist-info/WHEEL
clck_ru_api-1.0.0.dist-info/top_level.txt
clck_ru_api-1.0.0.dist-info/RECORD
