Metadata-Version: 2.1
Name: clck-ru-api
Version: 1.0.0
Summary: import clck.ru 
Author: wer310Libs
Author-email: oficalkapudovo@gmail.com
License: UNKNOWN
Platform: UNKNOWN
